agentx/__init__.py
agentx/agentx.py
agentx/util.py
agentx/version.py
agentx/resources/__init__.py
agentx/resources/agent.py
agentx/resources/conversation.py
agentx/resources/workforce.py
agentx_python-0.4.8.dist-info/licenses/LICENSE
agentx_python-0.4.8.dist-info/METADATA
agentx_python-0.4.8.dist-info/WHEEL
agentx_python-0.4.8.dist-info/top_level.txt
agentx_python-0.4.8.dist-info/RECORD
