Metadata-Version: 2.4
Name: agentx-python
Version: 0.4.8
Summary: Official Python SDK for AgentX (https://www.agentx.so/)
Home-page: https://github.com/AgentX-ai/AgentX-python-sdk
Author: Robin Wang and AgentX Team
Author-email: contact@agentx.so
Classifier: Programming Language :: Python :: 3
Classifier: License :: OSI Approved :: MIT License
Classifier: Operating System :: OS Independent
Requires-Python: >=3.6
License-File: LICENSE
Requires-Dist: urllib3>=1.26.11
Requires-Dist: certifi
Requires-Dist: requests
Requires-Dist: pydantic
Requires-Dist: pydantic_core
Dynamic: author
Dynamic: author-email
Dynamic: classifier
Dynamic: description
Dynamic: description-content-type
Dynamic: home-page
Dynamic: license-file
Dynamic: requires-dist
Dynamic: requires-python
Dynamic: summary
